jerry_finance_charts_apple/__init__.py
jerry_finance_charts_apple/main.py
jerry_finance_charts_apple-0.3.1.dist-info/METADATA
jerry_finance_charts_apple-0.3.1.dist-info/WHEEL
jerry_finance_charts_apple-0.3.1.dist-info/top_level.txt
jerry_finance_charts_apple-0.3.1.dist-info/RECORD
