Metadata-Version: 2.1
Name: jerry-finance-charts-apple
Version: 0.3.1
Summary: A simple python package to run specific actions on a csv file for apple stock prices
Author: Jerry Osorio
License: The Unlicense
Classifier: Topic :: Utilities
Requires-Python: >=3.10, <3.12
Requires-Dist: pandas (>=2.2)
Requires-Dist: plotly (>=5.23)
